flask_getenvvalue/__init__.py
flask_getenvvalue-0.1.0.dist-info/LICENSE
flask_getenvvalue-0.1.0.dist-info/WHEEL
flask_getenvvalue-0.1.0.dist-info/METADATA
flask_getenvvalue-0.1.0.dist-info/RECORD
