Metadata-Version: 2.1
Name: flask-getenvvalue
Version: 0.1.0
Summary: Loading a values from environment variable and set to app.config. 
Author: Yusuke Ohshima
Author-email: ohshima.yusuke@yukke.org
Requires-Python: >=3.6,<4.0
Classifier: Programming Language :: Python :: 3
Classifier: Programming Language :: Python :: 3.6
Classifier: Programming Language :: Python :: 3.7
Classifier: Programming Language :: Python :: 3.8
Classifier: Programming Language :: Python :: 3.9
Requires-Dist: Flask (>=2.0.0,<3.0.0)
